redqlite/__init__.py
redqlite/config.py
redqlite/producer.py
redqlite/redis.py
redqlite/subscriber.py
redqlite/utils.py
redqlite/worker.py
redqlite-1.0.0.dist-info/licenses/LICENSE
redqlite-1.0.0.dist-info/METADATA
redqlite-1.0.0.dist-info/WHEEL
redqlite-1.0.0.dist-info/top_level.txt
redqlite-1.0.0.dist-info/RECORD
