Metadata-Version: 2.4
Name: redqlite
Version: 1.0.0
Summary: A lightweight Messaging queue implementation using Redis for producer-worker-subscriber messaging.
Author: Shashank Gandhi
License-Expression: MIT
Project-URL: Homepage, https://github.com/shashankgandhi1/redqlite
Project-URL: Bug Tracker, https://github.com/shashankgandhi1/redqlite/issues
Classifier: Programming Language :: Python :: 3
Classifier: Operating System :: OS Independent
Requires-Python: >=3.12
License-File: LICENSE
Requires-Dist: redis==6.2.0
Dynamic: license-file
